pipen_cli_ref.py
pipen_cli_ref-1.0.2.dist-info/METADATA
pipen_cli_ref-1.0.2.dist-info/WHEEL
pipen_cli_ref-1.0.2.dist-info/entry_points.txt
pipen_cli_ref-1.0.2.dist-info/licenses/LICENSE
pipen_cli_ref-1.0.2.dist-info/RECORD
