Metadata-Version: 2.4
Name: pipen-cli-ref
Version: 1.0.2
Summary: Make API reference documentation for pipen pipeline/processes
License: MIT
License-File: LICENSE
Author: pwwang
Author-email: 1188067+pwwang@users.noreply.github.com
Requires-Python: >=3.9,<4.0
Classifier: License :: OSI Approved :: MIT License
Classifier: Programming Language :: Python :: 3
Classifier: Programming Language :: Python :: 3.9
Classifier: Programming Language :: Python :: 3.10
Classifier: Programming Language :: Python :: 3.11
Classifier: Programming Language :: Python :: 3.12
Classifier: Programming Language :: Python :: 3.13
Classifier: Programming Language :: Python :: 3.14
Requires-Dist: pipen (==1.1.*)
Requires-Dist: pipen-annotate (>=1.0,<2.0)
